sllurp_gui/__init__.py
sllurp_gui/__main__.py
sllurp_gui/main.py
sllurp_gui/version.py
sllurp_gui-1.0.0.dist-info/LICENSE.txt
sllurp_gui-1.0.0.dist-info/METADATA
sllurp_gui-1.0.0.dist-info/WHEEL
sllurp_gui-1.0.0.dist-info/entry_points.txt
sllurp_gui-1.0.0.dist-info/top_level.txt
sllurp_gui-1.0.0.dist-info/RECORD
